{"title":"Stichprobenziehung","markdown":{"yaml":{"title":"Stichprobenziehung"},"headingText":"Grundlagen der Stichprobenziehung","containsRefs":false,"markdown":"\n\n\nEine Stichprobe ist eine Teilmenge der Grundgesamtheit, die für eine Untersuchung ausgewählt wird.\n\n## Ziele der Stichprobenziehung\n\n- Repräsentativität für die Grundgesamtheit\n- Ökonomische Durchführbarkeit\n- Generalisierbarkeit der Ergebnisse\n\n## Stichprobenarten\n\n### Zufallsstichproben (Probabilistische Stichproben)\n\n#### Einfache Zufallsstichprobe\nJedes Element der Grundgesamtheit hat die gleiche Wahrscheinlichkeit, ausgewählt zu werden.\n\n#### Geschichtete Stichprobe\nDie Grundgesamtheit wird in Schichten unterteilt, aus denen dann zufällig gezogen wird.\n\n#### Klumpenstichprobe\nNatürliche Gruppen (Klumpen) werden zufällig ausgewählt und vollständig untersucht.\n\n### Nicht-Zufallsstichproben\n\n#### Gelegenheitsstichprobe\nAuswahl nach Verfügbarkeit und Erreichbarkeit.\n\n#### Quota-Stichprobe\nAuswahl nach vorgegebenen Quoten für bestimmte Merkmale.\n\n## Stichprobengröße\n\nDie benötigte Stichprobengröße hängt ab von:\n\n- Gewünschter statistischer Power (üblicherweise .80)\n- Erwarteter Effektgröße\n- Signifikanzniveau (üblicherweise α = .05)\n- Variabilität in der Population\n\n"},"formats":{"html":{"execute":{"fig-width":7,"fig-height":5,"fig-format":"retina","fig-dpi":96,"df-print":"default","error":false,"eval":true,"cache":null,"freeze":false,"echo":false,"output":true,"warning":false,"include":true,"keep-md":false,"keep-ipynb":false,"ipynb":null,"enabled":null,"daemon":null,"daemon-restart":false,"debug":false,"ipynb-filters":[],"message":false,"engine":"markdown"},"render":{"keep-tex":false,"keep-yaml":false,"keep-source":false,"keep-hidden":false,"prefer-html":false,"output-divs":true,"output-ext":"html","fig-align":"default","fig-pos":null,"fig-env":null,"code-fold":"none","code-overflow":"scroll","code-link":false,"code-line-numbers":false,"code-tools":false,"tbl-colwidths":"auto","merge-includes":true,"latex-auto-mk":true,"latex-auto-install":true,"latex-clean":true,"latex-max-runs":10,"latex-makeindex":"makeindex","latex-makeindex-opts":[],"latex-tlmgr-opts":[],"latex-input-paths":[],"latex-output-dir":null,"link-external-icon":false,"link-external-newwindow":false,"self-contained-math":false,"format-resources":[]},"pandoc":{"standalone":true,"wrap":"none","default-image-extension":"png","to":"html","toc":true,"output-file":"stichprobe.html"},"language":{},"metadata":{"lang":"en","fig-responsive":true,"quarto-version":"1.0.16","editor":"source","theme":"default","title":"Stichprobenziehung"},"extensions":{"book":{"multiFile":true}}}}}